samuelcolvin_aicli.py
samuelcolvin_aicli-0.8.0.dist-info/METADATA
samuelcolvin_aicli-0.8.0.dist-info/WHEEL
samuelcolvin_aicli-0.8.0.dist-info/entry_points.txt
samuelcolvin_aicli-0.8.0.dist-info/licenses/LICENSE
samuelcolvin_aicli-0.8.0.dist-info/RECORD
